sagemaker/__init__.py
sagemaker/ai_registry/__init__.py
sagemaker/ai_registry/air_constants.py
sagemaker/ai_registry/air_hub.py
sagemaker/ai_registry/air_hub_entity.py
sagemaker/ai_registry/air_utils.py
sagemaker/ai_registry/dataset.py
sagemaker/ai_registry/dataset_format_detector.py
sagemaker/ai_registry/dataset_utils.py
sagemaker/ai_registry/dataset_validation.py
sagemaker/ai_registry/evaluator.py
sagemaker/ai_registry/utils.py
sagemaker/ai_registry/schemas/converse.json
sagemaker/ai_registry/schemas/dpo.json
sagemaker/ai_registry/schemas/genqa.json
sagemaker/ai_registry/schemas/hf_preference.json
sagemaker/ai_registry/schemas/hf_prompt_completion.json
sagemaker/ai_registry/schemas/openai_chat.json
sagemaker/ai_registry/schemas/verl.json
sagemaker/train/__init__.py
sagemaker/train/base_trainer.py
sagemaker/train/common.py
sagemaker/train/configs.py
sagemaker/train/constants.py
sagemaker/train/defaults.py
sagemaker/train/distributed.py
sagemaker/train/dpo_trainer.py
sagemaker/train/model_trainer.py
sagemaker/train/rlaif_trainer.py
sagemaker/train/rlvr_trainer.py
sagemaker/train/sft_trainer.py
sagemaker/train/templates.py
sagemaker/train/tuner.py
sagemaker/train/types.py
sagemaker/train/utils.py
sagemaker/train/aws_batch/__init__.py
sagemaker/train/aws_batch/batch_api_helper.py
sagemaker/train/aws_batch/boto_client.py
sagemaker/train/aws_batch/constants.py
sagemaker/train/aws_batch/exception.py
sagemaker/train/aws_batch/training_queue.py
sagemaker/train/aws_batch/training_queued_job.py
sagemaker/train/common_utils/constants.py
sagemaker/train/common_utils/finetune_utils.py
sagemaker/train/common_utils/get_mlflow_endpoint.py
sagemaker/train/common_utils/mlflow_metrics_util.py
sagemaker/train/common_utils/model_resolution.py
sagemaker/train/common_utils/recipe_utils.py
sagemaker/train/common_utils/show_results_utils.py
sagemaker/train/common_utils/trainer_wait.py
sagemaker/train/container_drivers/__init__.py
sagemaker/train/container_drivers/common/__init__.py
sagemaker_train-1.3.0.dist-info/licenses/LICENSE
sagemaker_train-1.3.0.dist-info/METADATA
sagemaker_train-1.3.0.dist-info/WHEEL
sagemaker_train-1.3.0.dist-info/top_level.txt
sagemaker_train-1.3.0.dist-info/RECORD
