Metadata-Version: 2.4
Name: sagemaker-train
Version: 1.3.0
Summary: Open source library for training and deploying models on Amazon SageMaker.
Author: Amazon Web Services
Project-URL: Homepage, https://github.com/aws/sagemaker-python-sdk
Keywords: AI,AWS,Amazon,ML,MXNet,Tensorflow,PyTorch,HuggingFace
Classifier: Development Status :: 3 - Alpha
Classifier: Intended Audience :: Developers
Classifier: Natural Language :: English
Classifier: Programming Language :: Python
Classifier: Programming Language :: Python :: 3.9
Classifier: Programming Language :: Python :: 3.10
Classifier: Programming Language :: Python :: 3.11
Classifier: Programming Language :: Python :: 3.12
Requires-Python: >=3.9
License-File: LICENSE
Requires-Dist: sagemaker-core>=2.3.0
Requires-Dist: graphene<4,>=3
Requires-Dist: typing_extensions>=4.9.0
Requires-Dist: tblib>=1.7.0
Requires-Dist: PyYAML<7.0,>=6.0
Requires-Dist: paramiko>=2.11.0
Requires-Dist: jinja2<4.0,>=3.0
Requires-Dist: sagemaker-mlflow<1.0.0,>=0.0.1
Requires-Dist: mlflow<4.0.0,>=3.0.0
Requires-Dist: nest_asyncio>=1.5.0
Provides-Extra: test
Requires-Dist: pytest; extra == "test"
Requires-Dist: pytest-cov; extra == "test"
Requires-Dist: pytest-xdist; extra == "test"
Requires-Dist: mock; extra == "test"
Requires-Dist: pydantic; extra == "test"
Requires-Dist: pandas; extra == "test"
Requires-Dist: scipy; extra == "test"
Requires-Dist: omegaconf; extra == "test"
Requires-Dist: graphene; extra == "test"
Requires-Dist: IPython; extra == "test"
Dynamic: license-file
